fibinacci/rtl.v
module rtl(clk,rst,out);
	input clk,rst;
	output reg [7:0]  out;

	reg [7:0] q,q_prev_state;

	always @(posedge clk)
		begin
			if(rst)
				begin
					q <= 1;
					q_prev_state <= 1;
					out <= 1;
				end

			else
				begin
					out <= q + q_prev_state;
					q_prev_state <= q;
					q <= q + q_prev_state;
				end
					
		end
endmodule

fibinacci/rtl_tb.v
module rtl_tb();
	reg clk,rst;
	wire [7:0] out;

	rtl DUT(.clk(clk),.rst(rst),.out(out));

	parameter timeperiod = 10;
	
	always
		begin
			clk = 1'b0;
			#(timeperiod/2);
			clk = 1'b1;
			#(timeperiod/2);
		end
	
	task reset;
		begin
			@(negedge clk)
			rst = 1'b1;
			@(negedge clk)
			rst = 1'b0;
		end
	endtask

	initial 
		begin
			reset;
			#200;
			$finish;
		end
	initial
		begin
			$dumpfile("waveform.vcd");
			$dumpvars(0,rtl_tb);
		end
		
endmodule

fibinacci/waveform.vcd
$date
	Sun May 17 13:41:23 2026
$end
$version
	Icarus Verilog
$end
$timescale
	1s
$end
$scope module rtl_tb $end
$var wire 8 ! out [7:0] $end
$var reg 1 " clk $end
$var reg 1 # rst $end
$scope module DUT $end
$var wire 1 " clk $end
$var wire 1 # rst $end
$var reg 8 $ out [7:0] $end
$var reg 8 % q [7:0] $end
$var reg 8 & q_prev_state [7:0] $end
$upscope $end
$scope task reset $end
$upscope $end
$upscope $end
$enddefinitions $end
#0
$dumpvars
bx &
bx %
bx $
x#
0"
bx !
$end
#5
1"
#10
1#
0"
#15
b1 !
b1 $
b1 &
b1 %
1"
#20
0#
0"
#25
b10 %
b10 !
b10 $
1"
#30
0"
#35
b11 %
b10 &
b11 !
b11 $
1"
#40
0"
#45
b101 %
b11 &
b101 !
b101 $
1"
#50
0"
#55
b1000 %
b101 &
b1000 !
b1000 $
1"
#60
0"
#65
b1101 %
b1000 &
b1101 !
b1101 $
1"
#70
0"
#75
b10101 %
b1101 &
b10101 !
b10101 $
1"
#80
0"
#85
b100010 %
b10101 &
b100010 !
b100010 $
1"
#90
0"
#95
b110111 %
b100010 &
b110111 !
b110111 $
1"
#100
0"
#105
b1011001 %
b110111 &
b1011001 !
b1011001 $
1"
#110
0"
#115
b10010000 %
b1011001 &
b10010000 !
b10010000 $
1"
#120
0"
#125
b11101001 %
b10010000 &
b11101001 !
b11101001 $
1"
#130
0"
#135
b1111001 %
b11101001 &
b1111001 !
b1111001 $
1"
#140
0"
#145
b1100010 %
b1111001 &
b1100010 !
b1100010 $
1"
#150
0"
#155
b11011011 %
b1100010 &
b11011011 !
b11011011 $
1"
#160
0"
#165
b111101 %
b11011011 &
b111101 !
b111101 $
1"
#170
0"
#175
b11000 %
b111101 &
b11000 !
b11000 $
1"
#180
0"
#185
b1010101 %
b11000 &
b1010101 !
b1010101 $
1"
#190
0"
#195
b1101101 %
b1010101 &
b1101101 !
b1101101 $
1"
#200
0"
#205
b11000010 %
b1101101 &
b11000010 !
b11000010 $
1"
#210
0"
#215
b101111 %
b11000010 &
b101111 !
b101111 $
1"
