f_by_3_with_50%_dc/rtl.v
module rtl(rst,clk,out);
	input clk,rst;
	output out;

	reg [1:0] count;
	reg q,x;

	always @(posedge clk)
		begin
			if (rst)
				begin
					q  <= 1'b0;
					count <= 1'b0;
				end
			else if (count == 1'b0)
				begin
					q <= 1'b0;
					count <= count + 1'b1;
				end
			else if (count == 1'b1)
				begin
					q <= 1'b1;
					count <= count + 1'b1;
				end
			else
				begin
					q <= 1'b1;
					count <= 1'b0;
				end
		end

	always@ (negedge clk)
		begin
			if(rst)
				x <= 1'b0;
			else 
				x <= q;
		end

	assign out = x & q;

endmodule

f_by_2.5/rtl_tb.v
module rtl_tb();
	reg clk,rst;
	wire out;

	parameter timeperiod = 10;

	rtl DUT(.clk(clk),.rst(rst),.out(out));

	always
		begin
			clk = 1'b0;
			#(timeperiod/2);
			clk = 1'b1;
			#(timeperiod/2);
		end

	task reset;
		begin
			@(negedge clk)
			rst = 1'b1;
			@(negedge clk)
			rst = 1'b0;
		end
	endtask

	initial
		begin
			reset;
			#100;
			$finish;
		end

	initial
		begin
			$dumpfile("waveform.vcd");
			$dumpvars(0,rtl_tb);
		end

endmodule

f_by_3_with_50%_dc/waveform.vcd
$date
	Sat May 16 16:11:56 2026
$end
$version
	Icarus Verilog
$end
$timescale
	1s
$end
$scope module rtl_tb $end
$var wire 1 ! out $end
$var reg 1 " clk $end
$var reg 1 # rst $end
$scope module DUT $end
$var wire 1 " clk $end
$var wire 1 ! out $end
$var wire 1 # rst $end
$var reg 2 $ count [1:0] $end
$var reg 1 % q $end
$var reg 1 & x $end
$upscope $end
$scope task reset $end
$upscope $end
$upscope $end
$enddefinitions $end
#0
$dumpvars
x&
x%
bx $
x#
0"
x!
$end
#5
b0 $
1%
1"
#10
1!
1&
1#
0"
#15
0!
0%
1"
#20
0&
0#
0"
#25
b1 $
1"
#30
0"
#35
b10 $
1%
1"
#40
1!
1&
0"
#45
b0 $
1"
#50
0"
#55
0!
b1 $
0%
1"
#60
0&
0"
#65
b10 $
1%
1"
#70
1!
1&
0"
#75
b0 $
1"
#80
0"
#85
0!
b1 $
0%
1"
#90
0&
0"
#95
b10 $
1%
1"
#100
1!
1&
0"
#105
b0 $
1"
#110
0"
#115
0!
b1 $
0%
1"
#120
0&
0"
