f_by_2.5/rtl.v
module rtl(clk,rst,out);
	input clk,rst;
	output out;
	reg [2:0] count;

	always @(posedge clk or negedge clk)
		begin
			if (rst)
				count <= 1'b0;
			else if (count == 4)
				count <= 0;
			else
				count <= count + 1;
		end

	assign out = (count == 0);
endmodule

f_by_2.5/rtl_tb.v
module rtl_tb();
	reg clk,rst;
	wire out;

	parameter timeperiod = 10;

	rtl DUT(.clk(clk),.rst(rst),.out(out));

	always
		begin
			clk = 1'b0;
			#(timeperiod/2);
			clk = 1'b1;
			#(timeperiod/2);
		end

	task reset;
		begin
			@(negedge clk)
			rst = 1'b1;
			@(negedge clk)
			rst = 1'b0;
		end
	endtask

	initial
		begin
			reset;
			#100;
			$finish;
		end

	initial
		begin
			$dumpfile("waveform.vcd");
			$dumpvars(0,rtl_tb);
		end

endmodule

f_by_2.5/waveform.vcd
$date
	Sat May 16 22:38:47 2026
$end
$version
	Icarus Verilog
$end
$timescale
	1s
$end
$scope module rtl_tb $end
$var wire 1 ! out $end
$var reg 1 " clk $end
$var reg 1 # rst $end
$scope module DUT $end
$var wire 1 " clk $end
$var wire 1 # rst $end
$var wire 1 ! out $end
$var reg 3 $ count [2:0] $end
$upscope $end
$scope task reset $end
$upscope $end
$upscope $end
$enddefinitions $end
#0
$dumpvars
bx $
x#
0"
x!
$end
#5
1"
#10
1!
b0 $
1#
0"
#15
1"
#20
0!
b1 $
0#
0"
#25
b10 $
1"
#30
b11 $
0"
#35
b100 $
1"
#40
1!
b0 $
0"
#45
0!
b1 $
1"
#50
b10 $
0"
#55
b11 $
1"
#60
b100 $
0"
#65
1!
b0 $
1"
#70
0!
b1 $
0"
#75
b10 $
1"
#80
b11 $
0"
#85
b100 $
1"
#90
1!
b0 $
0"
#95
0!
b1 $
1"
#100
b10 $
0"
#105
b11 $
1"
#110
b100 $
0"
#115
1!
b0 $
1"
#120
0!
b1 $
0"
