multiply/halfadder.v
module halfadder(a,b,sum,carry);
	input a,b;
	output sum,carry;

	assign sum = a^b;
	assign carry = a&b;

endmodule

multiply/rtl.v
module rtl(a,b,out);
	input [1:0] a,b;
	output [3:0] out;

	wire w1,w2;

	halfadder HA1(.carry(w1),.a(a[1]),.b(b[0]));
	halfadder HA2(.carry(w2),.a(a[0]),.b(b[1]));

	halfadder HA3(.sum(out[1]),.carry(out[3]),.a(w1),.b(w2));

	assign out[0] = b[0] & a[0];
	assign out[2] = a[1] & b[1] & ~out[0];

endmodule

multiply/rtl_tb.v
module rtl_tb();
	reg [1:0] a,b;
	wire [3:0] out;

	integer i,j;

	rtl DUT(.a(a),.b(b),.out(out));

	initial
		begin
			for(i=0;i<4;i=i+1)
				begin
					for(j=0;j<4;j=j+1)
						begin
							a=i;
							b=j;
							#10;
						end
				end
			#100;
			$finish;
		end
	initial
		begin
			$dumpfile("waveform.vcd");
			$dumpvars(0,rtl_tb);
		end
endmodule

multiply/waveform.vcd
$date
	Sun May 17 11:56:57 2026
$end
$version
	Icarus Verilog
$end
$timescale
	1s
$end
$scope module rtl_tb $end
$var wire 4 ! out [3:0] $end
$var reg 2 " a [1:0] $end
$var reg 2 # b [1:0] $end
$var integer 32 $ i [31:0] $end
$var integer 32 % j [31:0] $end
$scope module DUT $end
$var wire 2 & a [1:0] $end
$var wire 2 ' b [1:0] $end
$var wire 1 ( w2 $end
$var wire 1 ) w1 $end
$var wire 4 * out [3:0] $end
$scope module HA1 $end
$var wire 1 + a $end
$var wire 1 , b $end
$var wire 1 ) carry $end
$var wire 1 - sum $end
$upscope $end
$scope module HA2 $end
$var wire 1 . a $end
$var wire 1 / b $end
$var wire 1 ( carry $end
$var wire 1 0 sum $end
$upscope $end
$scope module HA3 $end
$var wire 1 ) a $end
$var wire 1 ( b $end
$var wire 1 1 carry $end
$var wire 1 2 sum $end
$upscope $end
$upscope $end
$upscope $end
$enddefinitions $end
#0
$dumpvars
02
01
00
0/
0.
0-
0,
0+
b0 *
0)
0(
b0 '
b0 &
b0 %
b0 $
b0 #
b0 "
b0 !
$end
#10
1-
1,
b1 #
b1 '
b1 %
#20
0-
10
0,
1/
b10 #
b10 '
b10 %
#30
1-
1,
b11 #
b11 '
b11 %
#40
0-
0,
0/
1.
b0 #
b0 '
b1 "
b1 &
b1 $
b0 %
#50
1-
b1 !
b1 *
1,
b1 #
b1 '
b1 %
#60
12
0-
00
1(
b10 !
b10 *
0,
1/
b10 #
b10 '
b10 %
#70
1-
b11 !
b11 *
1,
b11 #
b11 '
b11 %
#80
02
0(
b0 !
b0 *
0,
0/
1+
0.
b0 #
b0 '
b10 "
b10 &
b10 $
b0 %
#90
b10 !
b10 *
12
0-
1)
1,
b1 #
b1 '
b1 %
#100
02
b100 !
b100 *
1-
0)
10
0,
1/
b10 #
b10 '
b10 %
#110
b110 !
b110 *
12
0-
1)
1,
b11 #
b11 '
b11 %
#120
02
b0 !
b0 *
1-
0)
0,
0/
1.
b0 #
b0 '
b11 "
b11 &
b11 $
b0 %
#130
12
0-
1)
b11 !
b11 *
1,
b1 #
b1 '
b1 %
#140
1-
0)
00
1(
b110 !
b110 *
0,
1/
b10 #
b10 '
b10 %
#150
02
11
0-
1)
b1001 !
b1001 *
1,
b11 #
b11 '
b11 %
#160
b100 $
b100 %
