counter78/counter.v
module counter(in,ld,rst,clk,out);
	input rst,clk,ld;
	output reg [6:0] out;
	input [6:0] in;

	always @(posedge clk)
		begin
			if (rst)
				out <= 7'd75;
			else if (ld)
				out <= in;
			else if (out == 7'd78)
				out <= 7'd75;
			else
				out <= out + 1'd1;
		end
endmodule

counter78/counter_tb.v
module counter_tb();
	reg [6:0] in;
	reg ld,rst,clk;
	wire [6:0] out;

	counter DUT(.in(in),.ld(ld),.rst(rst),.clk(clk),.out(out));

	always
		begin
			clk = 1'b0;
			#5;
			clk = 1'b1;
			#5;
		end

	task reset;
		begin
			@(negedge clk)
			rst = 1'b1;
			@(negedge clk)
			rst = 1'b0;
		end
	endtask

	task load(input [6:0] a);
		begin
			@(negedge clk)
			ld = 1'b1;
			in = a;
			@(negedge clk)
			ld = 1'b0;
			in = 7'b0;
		end
	endtask

	initial
		begin
			reset;
			#20;
			load(7'd76);
			#70;
			$finish;
		end

	initial
		begin
			$dumpfile("waveform.vcd");
			$dumpvars(0,counter_tb);
		end
endmodule

counter78/waveform.vcd
$date
	Wed May 13 06:49:54 2026
$end
$version
	Icarus Verilog
$end
$timescale
	1s
$end
$scope module counter_tb $end
$var wire 7 ! out [6:0] $end
$var reg 1 " clk $end
$var reg 7 # in [6:0] $end
$var reg 1 $ ld $end
$var reg 1 % rst $end
$scope module DUT $end
$var wire 1 " clk $end
$var wire 7 & in [6:0] $end
$var wire 1 $ ld $end
$var wire 1 % rst $end
$var reg 7 ' out [6:0] $end
$upscope $end
$scope task load $end
$var reg 7 ( a [6:0] $end
$upscope $end
$scope task reset $end
$upscope $end
$upscope $end
$enddefinitions $end
#0
$dumpvars
bx (
bx '
bx &
x%
x$
bx #
0"
bx !
$end
#5
1"
#10
1%
0"
#15
b1001011 !
b1001011 '
1"
#20
0%
0"
#25
b1001100 !
b1001100 '
1"
#30
0"
#35
b1001101 !
b1001101 '
1"
#40
b1001100 #
b1001100 &
1$
0"
b1001100 (
#45
b1001100 !
b1001100 '
1"
#50
b0 #
b0 &
0$
0"
#55
b1001101 !
b1001101 '
1"
#60
0"
#65
b1001110 !
b1001110 '
1"
#70
0"
#75
b1001011 !
b1001011 '
1"
#80
0"
#85
b1001100 !
b1001100 '
1"
#90
0"
#95
b1001101 !
b1001101 '
1"
#100
0"
#105
b1001110 !
b1001110 '
1"
#110
0"
#115
b1001011 !
b1001011 '
1"
