mul_freq/rtl.v
module rtl (
    input        clk,
    input        rst,
    input  [1:0] sel,
    output reg   out
);

reg [2:0] count;

always @(posedge clk)
begin
    if (rst)
        count <= 0;
    else
    begin
        case(sel)

            // F/2
            2'b00:
                if(count == 1)
                    count <= 0;
                else
                    count <= count + 1;

            // F/5
            2'b01,
            2'b10:
                if(count == 4)
                    count <= 0;
                else
                    count <= count + 1;

            // F/4
            2'b11:
                if(count == 3)
                    count <= 0;
                else
                    count <= count + 1;

        endcase
    end
end

always @(*)
begin
    case(sel)

        // F/2, 50%
        2'b00:
            out = (count < 1);

        // F/5, 40%
        2'b01:
            out = (count < 2);

        // F/5, 60%
        2'b10:
            out = (count < 3);

        // F/4, 50%
        2'b11:
            out = (count < 2);

        default:
            out = 0;

    endcase
end

endmodule

mul_freq/rtl_tb.v
module tb;

reg clk;
reg rst;
reg [1:0] sel;
wire out;

rtl dut (
    .clk(clk),
    .rst(rst),
    .sel(sel),
    .out(out)
);

// Clock generation (10 ns period)
initial
begin
    clk = 0;
    forever #5 clk = ~clk;
end

initial
begin
    $dumpfile("wave.vcd");
    $dumpvars(0,tb);

    rst = 1;
    sel = 2'b00;

    #20;
    rst = 0;

    // F/2, 50%
    sel = 2'b00;
    #100;

    // F/5, 40%
    sel = 2'b01;
    #100;

    // F/5, 60%
    sel = 2'b10;
    #100;

    // F/4, 50%
    sel = 2'b11;
    #100;

    $finish;
end

endmodule

mul_freq/wave.vcd
$date
	Sun May 31 17:02:07 2026
$end
$version
	Icarus Verilog
$end
$timescale
	1s
$end
$scope module tb $end
$var wire 1 ! out $end
$var reg 1 " clk $end
$var reg 1 # rst $end
$var reg 2 $ sel [1:0] $end
$scope module dut $end
$var wire 1 " clk $end
$var wire 1 # rst $end
$var wire 2 % sel [1:0] $end
$var reg 3 & count [2:0] $end
$var reg 1 ! out $end
$upscope $end
$upscope $end
$enddefinitions $end
#0
$dumpvars
bx &
b0 %
b0 $
1#
0"
x!
$end
#5
1!
b0 &
1"
#10
0"
#15
1"
#20
0"
0#
#25
0!
b1 &
1"
#30
0"
#35
1!
b0 &
1"
#40
0"
#45
0!
b1 &
1"
#50
0"
#55
1!
b0 &
1"
#60
0"
#65
0!
b1 &
1"
#70
0"
#75
1!
b0 &
1"
#80
0"
#85
0!
b1 &
1"
#90
0"
#95
1!
b0 &
1"
#100
0"
#105
0!
b1 &
1"
#110
0"
#115
1!
b0 &
1"
#120
0"
b1 $
b1 %
#125
b1 &
1"
#130
0"
#135
0!
b10 &
1"
#140
0"
#145
b11 &
1"
#150
0"
#155
b100 &
1"
#160
0"
#165
1!
b0 &
1"
#170
0"
#175
b1 &
1"
#180
0"
#185
0!
b10 &
1"
#190
0"
#195
b11 &
1"
#200
0"
#205
b100 &
1"
#210
0"
#215
1!
b0 &
1"
#220
0"
b10 $
b10 %
#225
b1 &
1"
#230
0"
#235
b10 &
1"
#240
0"
#245
0!
b11 &
1"
#250
0"
#255
b100 &
1"
#260
0"
#265
1!
b0 &
1"
#270
0"
#275
b1 &
1"
#280
0"
#285
b10 &
1"
#290
0"
#295
0!
b11 &
1"
#300
0"
#305
b100 &
1"
#310
0"
#315
1!
b0 &
1"
#320
0"
b11 $
b11 %
#325
b1 &
1"
#330
0"
#335
0!
b10 &
1"
#340
0"
#345
b11 &
1"
#350
0"
#355
1!
b0 &
1"
#360
0"
#365
b1 &
1"
#370
0"
#375
0!
b10 &
1"
#380
0"
#385
b11 &
1"
#390
0"
#395
1!
b0 &
1"
#400
0"
#405
b1 &
1"
#410
0"
#415
0!
b10 &
1"
