40Mhz/rtl.v
module rtl(clk,rst,out1,out2,out3);
	input clk,rst;
	output out2;
	output out1,out3;

	reg [2:0] count,count1,count2;

	always @(posedge clk or negedge clk)
		begin
			if (rst)
				count <= 1'b0;
			else if (count == 4)
				count <= 0;
			else
				count <= count + 1;
		end

	assign out1 = (count < 2);

	
	always @(posedge clk)
		begin
			if (rst)
				count1 <= 1'b0;
			else if (count1 == 4)
				count1 <= 0;
			else
				count1 <= count1 + 1;
		end

	assign out2 = (count1 < 2);

	
	always @(posedge clk)
		begin
			if (rst)
				count2 <= 1'b0;
			else if (count2 == 4)
				count2 <= 0;
			else
				count2 <= count2 + 1;
		end
	assign out3 = (count2 < 1);

endmodule

40Mhz/rtl_tb.v
module rtl_tb();
	reg clk,rst;
	wire out1,out2,out3;

	parameter timeperiod = 10;

	rtl DUT(.clk(clk),.rst(rst),.out1(out1),.out2(out2),.out3(out3));

	always
		begin
			clk = 1'b0;
			#(timeperiod/2);
			clk = 1'b1;
			#(timeperiod/2);
		end

	task reset;
		begin
			@(negedge clk)
			rst = 1'b1;
			@(negedge clk)
			rst = 1'b0;
		end
	endtask

	initial
		begin
			reset;
			#100;
			$finish;
		end

	initial
		begin
			$dumpfile("waveform.vcd");
			$dumpvars(0,rtl_tb);
		end

endmodule

40Mhz/waveform.vcd
$date
	Sat May 16 22:21:26 2026
$end
$version
	Icarus Verilog
$end
$timescale
	1s
$end
$scope module rtl_tb $end
$var wire 1 ! out3 $end
$var wire 1 " out2 $end
$var wire 1 # out1 $end
$var reg 1 $ clk $end
$var reg 1 % rst $end
$scope module DUT $end
$var wire 1 $ clk $end
$var wire 1 % rst $end
$var wire 1 ! out3 $end
$var wire 1 " out2 $end
$var wire 1 # out1 $end
$var reg 3 & count [2:0] $end
$var reg 3 ' count1 [2:0] $end
$var reg 3 ( count2 [2:0] $end
$upscope $end
$scope task reset $end
$upscope $end
$upscope $end
$enddefinitions $end
#0
$dumpvars
bx (
bx '
bx &
x%
0$
x#
x"
x!
$end
#5
1$
#10
1#
b0 &
1%
0$
#15
1!
b0 (
1"
b0 '
1$
#20
b1 &
0%
0$
#25
b1 '
0!
b1 (
0#
b10 &
1$
#30
b11 &
0$
#35
b10 (
0"
b10 '
b100 &
1$
#40
1#
b0 &
0$
#45
b11 '
b11 (
b1 &
1$
#50
0#
b10 &
0$
#55
b100 (
b100 '
b11 &
1$
#60
b100 &
0$
#65
1"
b0 '
1!
b0 (
1#
b0 &
1$
#70
b1 &
0$
#75
0!
b1 (
b1 '
0#
b10 &
1$
#80
b11 &
0$
#85
0"
b10 '
b10 (
b100 &
1$
#90
1#
b0 &
0$
#95
b11 (
b11 '
b1 &
1$
#100
0#
b10 &
0$
#105
b100 '
b100 (
b11 &
1$
#110
b100 &
0$
#115
1!
b0 (
1"
b0 '
1#
b0 &
1$
#120
b1 &
0$
