8_bit_up_down_counter/rtl.v
module rtl(clk,rst,in,ld,up_down,out);
	input clk,rst,up_down,ld;
	output reg [7:0] out;
	input [7:0] in;


	always @(posedge clk)
	begin
		if(rst)
		begin
			out <= 8'b0;
		end
		else if(ld == 1)
			out <= in;
		else if (up_down == 0)
			out <= out + 1'b1;
	        else if (up_down == 1)
			out <= out - 1'b1;
	end
endmodule

8_bit_up_down_counter/rtl_tb.v
module tb;

reg clk;
reg rst;
reg ld;
reg up_down;
reg [7:0] in;
wire [7:0] out;

// DUT Instantiation
rtl dut (
    .clk(clk),
    .rst(rst),
    .ld(ld),
    .up_down(up_down),
    .in(in),
    .out(out)
);

// Clock Generation (10 ns period)
initial begin
    clk = 0;
    forever #5 clk = ~clk;
end

// Stimulus
initial begin
    $dumpfile("counter.vcd");
    $dumpvars(0, tb);

    // Initialize
    rst     = 1;
    ld      = 0;
    up_down = 0;
    in      = 8'h00;

    // Apply reset
    #12 rst = 0;

    // Load 25
    @(posedge clk);
    ld = 1;
    in = 8'd25;

    @(posedge clk);
    ld = 0;

    // Count UP for 5 clocks
    up_down = 0;
    repeat(5) @(posedge clk);

    // Count DOWN for 5 clocks
    up_down = 1;
    repeat(5) @(posedge clk);

    // Load another value
    @(posedge clk);
    ld = 1;
    in = 8'd250;

    @(posedge clk);
    ld = 0;

    // Count UP for 3 clocks
    up_down = 1;
    repeat(3) @(posedge clk);

    #200;
    $finish;
end

endmodule

8_bit_up_down_counter/counter.vcd
$date
	Sun May 31 18:27:36 2026
$end
$version
	Icarus Verilog
$end
$timescale
	1s
$end
$scope module tb $end
$var wire 8 ! out [7:0] $end
$var reg 1 " clk $end
$var reg 8 # in [7:0] $end
$var reg 1 $ ld $end
$var reg 1 % rst $end
$var reg 1 & up_down $end
$scope module dut $end
$var wire 1 " clk $end
$var wire 8 ' in [7:0] $end
$var wire 1 $ ld $end
$var wire 1 % rst $end
$var wire 1 & up_down $end
$var reg 8 ( out [7:0] $end
$upscope $end
$upscope $end
$enddefinitions $end
#0
$dumpvars
bx (
b0 '
0&
1%
0$
b0 #
0"
bx !
$end
#5
b0 !
b0 (
1"
#10
0"
#12
0%
#15
b11001 !
b11001 (
b11001 #
b11001 '
1$
1"
#20
0"
#25
0$
1"
#30
0"
#35
b11010 !
b11010 (
1"
#40
0"
#45
b11011 !
b11011 (
1"
#50
0"
#55
b11100 !
b11100 (
1"
#60
0"
#65
b11101 !
b11101 (
1"
#70
0"
#75
b11100 !
b11100 (
1&
1"
#80
0"
#85
b11011 !
b11011 (
1"
#90
0"
#95
b11010 !
b11010 (
1"
#100
0"
#105
b11001 !
b11001 (
1"
#110
0"
#115
b11000 !
b11000 (
1"
#120
0"
#125
b10111 !
b10111 (
1"
#130
0"
#135
b11111010 !
b11111010 (
b11111010 #
b11111010 '
1$
1"
#140
0"
#145
0$
1"
#150
0"
#155
b11111001 !
b11111001 (
1"
#160
0"
#165
b11111000 !
b11111000 (
1"
#170
0"
#175
b11110111 !
b11110111 (
1"
#180
0"
#185
b11110110 !
b11110110 (
1"
#190
0"
#195
b11110101 !
b11110101 (
1"
#200
0"
#205
b11110100 !
b11110100 (
1"
#210
0"
#215
b11110011 !
b11110011 (
1"
#220
0"
#225
b11110010 !
b11110010 (
1"
#230
0"
#235
b11110001 !
b11110001 (
1"
#240
0"
#245
b11110000 !
b11110000 (
1"
#250
0"
#255
b11101111 !
b11101111 (
1"
#260
0"
#265
b11101110 !
b11101110 (
1"
#270
0"
#275
b11101101 !
b11101101 (
1"
#280
0"
#285
b11101100 !
b11101100 (
1"
#290
0"
#295
b11101011 !
b11101011 (
1"
#300
0"
#305
b11101010 !
b11101010 (
1"
#310
0"
#315
b11101001 !
b11101001 (
1"
#320
0"
#325
b11101000 !
b11101000 (
1"
#330
0"
#335
b11100111 !
b11100111 (
1"
#340
0"
#345
b11100110 !
b11100110 (
1"
#350
0"
#355
b11100101 !
b11100101 (
1"
#360
0"
#365
b11100100 !
b11100100 (
1"
#370
0"
#375
b11100011 !
b11100011 (
1"
